pie/__init__.py
pie/__main__.py
pie/python_insert_env.py
pie/version.py
python_pie-0.2.4.dist-info/LICENSE
python_pie-0.2.4.dist-info/METADATA
python_pie-0.2.4.dist-info/WHEEL
python_pie-0.2.4.dist-info/top_level.txt
python_pie-0.2.4.dist-info/RECORD
