Metadata-Version: 2.1
Name: python-pie
Version: 0.2.4
Summary: Parse static files such as YAML and insert in them data from environment variables
Home-page: https://github.com/igorMIA/python-pie
Author: Igor Matchenko
Author-email: igor@matchenko.com
License: UNKNOWN
Keywords: environment variables,deployments,settings,env,configurations,python,pie
Platform: UNKNOWN
Classifier: Development Status :: 4 - Beta
Classifier: Programming Language :: Python :: 3.7
Classifier: Programming Language :: Python :: 3.8
Classifier: Programming Language :: Python :: 3.9
Classifier: Intended Audience :: Developers
Classifier: Intended Audience :: System Administrators
Classifier: License :: OSI Approved :: BSD License
Classifier: Operating System :: OS Independent
Classifier: Topic :: System :: Systems Administration
Classifier: Topic :: Utilities
Requires-Python: >=3.7
License-File: LICENSE
